plusoft_api/__init__.py
plusoft_api/helpers/__init__.py
plusoft_api/helpers/api_endpoint.py
plusoft_api/helpers/base_requests.py
plusoft_api/models/aux.py
plusoft_api/models/consult.py
plusoft_api/models/users.py
plusoft_api/scripts/__init__.py
plusoft_api/scripts/consult.py
plusoft_api/scripts/payloads.py
plusoft_api/scripts/plusoft_api_client.py
plusoft_api/scripts/users.py
plusoft_api/utils/__init__.py
plusoft_api/utils/aux_functions.py
plusoft_api/utils/aux_types.py
plusoft_api-0.1.3.dist-info/LICENSE
plusoft_api-0.1.3.dist-info/METADATA
plusoft_api-0.1.3.dist-info/WHEEL
plusoft_api-0.1.3.dist-info/RECORD
