Metadata-Version: 2.1
Name: plusoft-api
Version: 0.1.3
Summary: 
Home-page: https://github.com/people-analytics-tech/plusoft-api
License: MIT
Author: stone_people_analytics
Author-email: systems-techpeople@stone.com.br
Maintainer: Diogo56
Maintainer-email: diogo.amorim2001@gmail.com
Requires-Python: >=3.9,<4.0
Classifier: License :: OSI Approved :: MIT License
Classifier: Programming Language :: Python :: 3
Classifier: Programming Language :: Python :: 3.9
Classifier: Programming Language :: Python :: 3.10
Classifier: Programming Language :: Python :: 3.11
Classifier: Programming Language :: Python :: 3.12
Requires-Dist: requests (>=2.31.0,<3.0.0)
Requires-Dist: typing-extensions (>=4.10.0,<5.0.0)
Project-URL: Repository, https://github.com/people-analytics-tech/plusoft-api
